HW2/adder.t.v
// Adder testbench
`timescale 1 ns / 1 ps
`include "adder.v"

module testFullAdder();
    reg a, b, carryin;
    wire sum, carryout, xor0, and0, and1;

    //behavioralFullAdder adder (sum, carryout, a, b, carryin);
    structuralFullAdder adder (sum, carryout, a, b, carryin, xor0, and0, and1); // Swap after testing

    initial begin
    $dumpfile("adder.vcd");
    $dumpvars;

    $display("a  b in | Out Sum| Expected Output");
    a = 0;b = 0; carryin = 0; #1000
    $display("%b  %b  %b |  %b   %b | All False", a, b, carryin, carryout, sum);
    a = 0;b = 0; carryin = 1; #1000
    $display("%b  %b  %b |  %b   %b | Sum Only ", a, b, carryin, carryout, sum);
    a = 1;b = 0; carryin = 0; #1000
    $display("%b  %b  %b |  %b   %b | Sum Only", a, b, carryin, carryout, sum);
    a = 1;b = 0; carryin = 1; #1000
    $display("%b  %b  %b |  %b   %b | Carryout Only ", a, b, carryin, carryout, sum);
    a = 0;b = 1; carryin = 0; #1000
    $display("%b  %b  %b |  %b   %b | Sum Only", a, b, carryin, carryout, sum);
    a = 0;b = 1; carryin = 1; #1000
    $display("%b  %b  %b |  %b   %b | Carryout Only ", a, b, carryin, carryout, sum);
    a = 1;b = 1; carryin = 0; #1000
    $display("%b  %b  %b |  %b   %b | Carryout Only", a, b, carryin, carryout, sum);
    a = 1;b = 1; carryin = 1; #1000
    $display("%b  %b  %b |  %b   %b | Both True ", a, b, carryin, carryout, sum);
    $finish();
    end
endmodule

HW2/adder.v
// Adder circuit
`define AND and #50
`define OR or #50
`define XOR xor #50
`define NOT not #50

module behavioralFullAdder
(
    output sum,
    output carryout,
    input a,
    input b,
    input carryin
);
    // Uses concatenation operator and built-in '+'
    assign {carryout, sum}=a+b+carryin;
endmodule

module structuralFullAdder
(
    output sum,
    output carryout,
    input a,
    input b,
    input carryin,
    output xor0, and0, and1

);
    // My decoder code here
    xor xorgate(xor0,a,b);
    and andgate(and0,a,b);
    xor xorgate(sum,xor0,carryin);
    and andgate(and1,xor0,carryin);
    or orgate(carryout,and0,and1);



endmodule

HW2/adder.vcd
$date
	Fri Sep 21 09:20:56 2018
$end
$version
	Icarus Verilog
$end
$timescale
	1ps
$end
$scope module behavioralFullAdder $end
$var wire 1 ! a $end
$var wire 1 " b $end
$var wire 1 # carryin $end
$var wire 1 $ sum $end
$var wire 1 % carryout $end
$upscope $end
$scope module testFullAdder $end
$var wire 1 & xor0 $end
$var wire 1 ' sum $end
$var wire 1 ( carryout $end
$var wire 1 ) and1 $end
$var wire 1 * and0 $end
$var reg 1 + a $end
$var reg 1 , b $end
$var reg 1 - carryin $end
$scope module adder $end
$var wire 1 + a $end
$var wire 1 * and0 $end
$var wire 1 ) and1 $end
$var wire 1 , b $end
$var wire 1 - carryin $end
$var wire 1 ( carryout $end
$var wire 1 ' sum $end
$var wire 1 & xor0 $end
$upscope $end
$upscope $end
$enddefinitions $end
#0
$dumpvars
0-
0,
0+
0*
0)
0(
0'
0&
x%
x$
z#
z"
z!
$end
#1000000
1'
1-
#2000000
1&
0-
1+
#3000000
1(
0'
1)
1-
#4000000
0(
1'
0)
0-
1,
0+
#5000000
1(
0'
1)
1-
#6000000
0)
0&
1*
0-
1+
#7000000
1'
1-
